Metadata-Version: 2.1
Name: netbluemind
Version: 3.1.42825
Summary: Automatically generated client for BlueMind < 4 REST API. Check netbluemind4 for more recent releases
Home-page: http://git.blue-mind.net/bluemind/
Author: BlueMind team
Author-email: contact@bluemind.net
Keywords: bluemind,rest,api,mail,groupware
Classifier: Development Status :: 5 - Production/Stable
Classifier: Intended Audience :: Developers
Classifier: Programming Language :: Python :: 2.7
Classifier: Programming Language :: Python :: 3
License-File: LICENSE.txt
Requires-Dist: requests
